<?xml version="1.0" encoding="UTF-8" ?>
<!DOCTYPE mapper PUBLIC "-//mybatis.org//DTD Mapper 3.0//EN" "http://mybatis.org/dtd/mybatis-3-mapper.dtd" >
<mapper namespace="com.lt.dao.mapper.AdAdvertiseFeedMapper" >
  <resultMap id="BaseResultMap" type="com.lt.dao.model.AdAdvertiseFeed" >
    <!--
      WARNING - @mbggenerated
      This element is automatically generated by MyBatis Generator, do not modify.
      This element was generated on Mon May 04 11:11:12 CST 2015.
    -->
    <id column="id" property="id" jdbcType="INTEGER" />
    <result column="ad_advertise_id" property="adAdvertiseId" jdbcType="INTEGER" />
    <result column="ad_group_id" property="adGroupId" jdbcType="INTEGER" />
    <result column="ad_campaign_id" property="adCampaignId" jdbcType="INTEGER" />
    <result column="company_id" property="companyId" jdbcType="INTEGER" />
    <result column="item_id" property="itemId" jdbcType="VARCHAR" />
    <result column="item_type" property="itemType" jdbcType="VARCHAR" />
    <result column="item_headline" property="itemHeadline" jdbcType="VARCHAR" />
    <result column="item_sub_headline" property="itemSubHeadline" jdbcType="VARCHAR" />
    <result column="item_description" property="itemDescription" jdbcType="VARCHAR" />
    <result column="item_address" property="itemAddress" jdbcType="VARCHAR" />
    <result column="price" property="price" jdbcType="DECIMAL" />
    <result column="image_url" property="imageUrl" jdbcType="VARCHAR" />
    <result column="item_category" property="itemCategory" jdbcType="INTEGER" />
    <result column="sale_price" property="salePrice" jdbcType="DECIMAL" />
    <result column="remarketing_url" property="remarketingUrl" jdbcType="VARCHAR" />
    <result column="destination_url" property="destinationUrl" jdbcType="VARCHAR" />
    <result column="final_url" property="finalUrl" jdbcType="VARCHAR" />
    <result column="create_time_utc" property="createTimeUtc" jdbcType="INTEGER" />
    <result column="create_user_id" property="createUserId" jdbcType="INTEGER" />
    <result column="update_time_utc" property="updateTimeUtc" jdbcType="INTEGER" />
    <result column="update_user_id" property="updateUserId" jdbcType="INTEGER" />
  </resultMap>
  <resultMap id="ResultMapWithBLOBs" type="com.lt.dao.model.AdAdvertiseFeed" extends="BaseResultMap" >
    <!--
      WARNING - @mbggenerated
      This element is automatically generated by MyBatis Generator, do not modify.
      This element was generated on Mon May 04 11:11:12 CST 2015.
    -->
    <result column="item_keywords" property="itemKeywords" jdbcType="LONGVARCHAR" />
  </resultMap>
  <sql id="Base_Column_List" >
    <!--
      WARNING - @mbggenerated
      This element is automatically generated by MyBatis Generator, do not modify.
      This element was generated on Mon May 04 11:11:12 CST 2015.
    -->
    id, ad_advertise_id, ad_group_id, ad_campaign_id, company_id, item_id, item_type, 
    item_headline, item_sub_headline, item_description, item_address, price, image_url, 
    item_category, sale_price, remarketing_url, destination_url, final_url, create_time_utc, 
    create_user_id, update_time_utc, update_user_id
  </sql>
  <sql id="Blob_Column_List" >
    <!--
      WARNING - @mbggenerated
      This element is automatically generated by MyBatis Generator, do not modify.
      This element was generated on Mon May 04 11:11:12 CST 2015.
    -->
    item_keywords
  </sql>
  <select id="selectByPrimaryKey" resultMap="ResultMapWithBLOBs" parameterType="java.lang.Integer" >
    <!--
      WARNING - @mbggenerated
      This element is automatically generated by MyBatis Generator, do not modify.
      This element was generated on Mon May 04 11:11:12 CST 2015.
    -->
    select 
    <include refid="Base_Column_List" />
    ,
    <include refid="Blob_Column_List" />
    from lt_ad_advertise_feed
    where id = #{id,jdbcType=INTEGER}
  </select>
  <delete id="deleteByPrimaryKey" parameterType="java.lang.Integer" >
    <!--
      WARNING - @mbggenerated
      This element is automatically generated by MyBatis Generator, do not modify.
      This element was generated on Mon May 04 11:11:12 CST 2015.
    -->
    delete from lt_ad_advertise_feed
    where id = #{id,jdbcType=INTEGER}
  </delete>
  <insert id="insert" parameterType="com.lt.dao.model.AdAdvertiseFeed" >
    <!--
      WARNING - @mbggenerated
      This element is automatically generated by MyBatis Generator, do not modify.
      This element was generated on Mon May 04 11:11:12 CST 2015.
    -->
    insert into lt_ad_advertise_feed (id, ad_advertise_id, ad_group_id, 
      ad_campaign_id, company_id, item_id, 
      item_type, item_headline, item_sub_headline, 
      item_description, item_address, price, 
      image_url, item_category, sale_price, 
      remarketing_url, destination_url, final_url, 
      create_time_utc, create_user_id, update_time_utc, 
      update_user_id, item_keywords)
    values (#{id,jdbcType=INTEGER}, #{adAdvertiseId,jdbcType=INTEGER}, #{adGroupId,jdbcType=INTEGER}, 
      #{adCampaignId,jdbcType=INTEGER}, #{companyId,jdbcType=INTEGER}, #{itemId,jdbcType=VARCHAR}, 
      #{itemType,jdbcType=VARCHAR}, #{itemHeadline,jdbcType=VARCHAR}, #{itemSubHeadline,jdbcType=VARCHAR}, 
      #{itemDescription,jdbcType=VARCHAR}, #{itemAddress,jdbcType=VARCHAR}, #{price,jdbcType=DECIMAL}, 
      #{imageUrl,jdbcType=VARCHAR}, #{itemCategory,jdbcType=INTEGER}, #{salePrice,jdbcType=DECIMAL}, 
      #{remarketingUrl,jdbcType=VARCHAR}, #{destinationUrl,jdbcType=VARCHAR}, #{finalUrl,jdbcType=VARCHAR}, 
      #{createTimeUtc,jdbcType=INTEGER}, #{createUserId,jdbcType=INTEGER}, #{updateTimeUtc,jdbcType=INTEGER}, 
      #{updateUserId,jdbcType=INTEGER}, #{itemKeywords,jdbcType=LONGVARCHAR})
  </insert>
  <insert id="insertSelective" parameterType="com.lt.dao.model.AdAdvertiseFeed" >
    <!--
      WARNING - @mbggenerated
      This element is automatically generated by MyBatis Generator, do not modify.
      This element was generated on Mon May 04 11:11:12 CST 2015.
    -->
    insert into lt_ad_advertise_feed
    <trim prefix="(" suffix=")" suffixOverrides="," >
      <if test="id != null" >
        id,
      </if>
      <if test="adAdvertiseId != null" >
        ad_advertise_id,
      </if>
      <if test="adGroupId != null" >
        ad_group_id,
      </if>
      <if test="adCampaignId != null" >
        ad_campaign_id,
      </if>
      <if test="companyId != null" >
        company_id,
      </if>
      <if test="itemId != null" >
        item_id,
      </if>
      <if test="itemType != null" >
        item_type,
      </if>
      <if test="itemHeadline != null" >
        item_headline,
      </if>
      <if test="itemSubHeadline != null" >
        item_sub_headline,
      </if>
      <if test="itemDescription != null" >
        item_description,
      </if>
      <if test="itemAddress != null" >
        item_address,
      </if>
      <if test="price != null" >
        price,
      </if>
      <if test="imageUrl != null" >
        image_url,
      </if>
      <if test="itemCategory != null" >
        item_category,
      </if>
      <if test="salePrice != null" >
        sale_price,
      </if>
      <if test="remarketingUrl != null" >
        remarketing_url,
      </if>
      <if test="destinationUrl != null" >
        destination_url,
      </if>
      <if test="finalUrl != null" >
        final_url,
      </if>
      <if test="createTimeUtc != null" >
        create_time_utc,
      </if>
      <if test="createUserId != null" >
        create_user_id,
      </if>
      <if test="updateTimeUtc != null" >
        update_time_utc,
      </if>
      <if test="updateUserId != null" >
        update_user_id,
      </if>
      <if test="itemKeywords != null" >
        item_keywords,
      </if>
    </trim>
    <trim prefix="values (" suffix=")" suffixOverrides="," >
      <if test="id != null" >
        #{id,jdbcType=INTEGER},
      </if>
      <if test="adAdvertiseId != null" >
        #{adAdvertiseId,jdbcType=INTEGER},
      </if>
      <if test="adGroupId != null" >
        #{adGroupId,jdbcType=INTEGER},
      </if>
      <if test="adCampaignId != null" >
        #{adCampaignId,jdbcType=INTEGER},
      </if>
      <if test="companyId != null" >
        #{companyId,jdbcType=INTEGER},
      </if>
      <if test="itemId != null" >
        #{itemId,jdbcType=VARCHAR},
      </if>
      <if test="itemType != null" >
        #{itemType,jdbcType=VARCHAR},
      </if>
      <if test="itemHeadline != null" >
        #{itemHeadline,jdbcType=VARCHAR},
      </if>
      <if test="itemSubHeadline != null" >
        #{itemSubHeadline,jdbcType=VARCHAR},
      </if>
      <if test="itemDescription != null" >
        #{itemDescription,jdbcType=VARCHAR},
      </if>
      <if test="itemAddress != null" >
        #{itemAddress,jdbcType=VARCHAR},
      </if>
      <if test="price != null" >
        #{price,jdbcType=DECIMAL},
      </if>
      <if test="imageUrl != null" >
        #{imageUrl,jdbcType=VARCHAR},
      </if>
      <if test="itemCategory != null" >
        #{itemCategory,jdbcType=INTEGER},
      </if>
      <if test="salePrice != null" >
        #{salePrice,jdbcType=DECIMAL},
      </if>
      <if test="remarketingUrl != null" >
        #{remarketingUrl,jdbcType=VARCHAR},
      </if>
      <if test="destinationUrl != null" >
        #{destinationUrl,jdbcType=VARCHAR},
      </if>
      <if test="finalUrl != null" >
        #{finalUrl,jdbcType=VARCHAR},
      </if>
      <if test="createTimeUtc != null" >
        #{createTimeUtc,jdbcType=INTEGER},
      </if>
      <if test="createUserId != null" >
        #{createUserId,jdbcType=INTEGER},
      </if>
      <if test="updateTimeUtc != null" >
        #{updateTimeUtc,jdbcType=INTEGER},
      </if>
      <if test="updateUserId != null" >
        #{updateUserId,jdbcType=INTEGER},
      </if>
      <if test="itemKeywords != null" >
        #{itemKeywords,jdbcType=LONGVARCHAR},
      </if>
    </trim>
  </insert>
  <update id="updateByPrimaryKeySelective" parameterType="com.lt.dao.model.AdAdvertiseFeed" >
    <!--
      WARNING - @mbggenerated
      This element is automatically generated by MyBatis Generator, do not modify.
      This element was generated on Mon May 04 11:11:12 CST 2015.
    -->
    update lt_ad_advertise_feed
    <set >
      <if test="adAdvertiseId != null" >
        ad_advertise_id = #{adAdvertiseId,jdbcType=INTEGER},
      </if>
      <if test="adGroupId != null" >
        ad_group_id = #{adGroupId,jdbcType=INTEGER},
      </if>
      <if test="adCampaignId != null" >
        ad_campaign_id = #{adCampaignId,jdbcType=INTEGER},
      </if>
      <if test="companyId != null" >
        company_id = #{companyId,jdbcType=INTEGER},
      </if>
      <if test="itemId != null" >
        item_id = #{itemId,jdbcType=VARCHAR},
      </if>
      <if test="itemType != null" >
        item_type = #{itemType,jdbcType=VARCHAR},
      </if>
      <if test="itemHeadline != null" >
        item_headline = #{itemHeadline,jdbcType=VARCHAR},
      </if>
      <if test="itemSubHeadline != null" >
        item_sub_headline = #{itemSubHeadline,jdbcType=VARCHAR},
      </if>
      <if test="itemDescription != null" >
        item_description = #{itemDescription,jdbcType=VARCHAR},
      </if>
      <if test="itemAddress != null" >
        item_address = #{itemAddress,jdbcType=VARCHAR},
      </if>
      <if test="price != null" >
        price = #{price,jdbcType=DECIMAL},
      </if>
      <if test="imageUrl != null" >
        image_url = #{imageUrl,jdbcType=VARCHAR},
      </if>
      <if test="itemCategory != null" >
        item_category = #{itemCategory,jdbcType=INTEGER},
      </if>
      <if test="salePrice != null" >
        sale_price = #{salePrice,jdbcType=DECIMAL},
      </if>
      <if test="remarketingUrl != null" >
        remarketing_url = #{remarketingUrl,jdbcType=VARCHAR},
      </if>
      <if test="destinationUrl != null" >
        destination_url = #{destinationUrl,jdbcType=VARCHAR},
      </if>
      <if test="finalUrl != null" >
        final_url = #{finalUrl,jdbcType=VARCHAR},
      </if>
      <if test="createTimeUtc != null" >
        create_time_utc = #{createTimeUtc,jdbcType=INTEGER},
      </if>
      <if test="createUserId != null" >
        create_user_id = #{createUserId,jdbcType=INTEGER},
      </if>
      <if test="updateTimeUtc != null" >
        update_time_utc = #{updateTimeUtc,jdbcType=INTEGER},
      </if>
      <if test="updateUserId != null" >
        update_user_id = #{updateUserId,jdbcType=INTEGER},
      </if>
      <if test="itemKeywords != null" >
        item_keywords = #{itemKeywords,jdbcType=LONGVARCHAR},
      </if>
    </set>
    where id = #{id,jdbcType=INTEGER}
  </update>
  <update id="updateByPrimaryKeyWithBLOBs" parameterType="com.lt.dao.model.AdAdvertiseFeed" >
    <!--
      WARNING - @mbggenerated
      This element is automatically generated by MyBatis Generator, do not modify.
      This element was generated on Mon May 04 11:11:12 CST 2015.
    -->
    update lt_ad_advertise_feed
    set ad_advertise_id = #{adAdvertiseId,jdbcType=INTEGER},
      ad_group_id = #{adGroupId,jdbcType=INTEGER},
      ad_campaign_id = #{adCampaignId,jdbcType=INTEGER},
      company_id = #{companyId,jdbcType=INTEGER},
      item_id = #{itemId,jdbcType=VARCHAR},
      item_type = #{itemType,jdbcType=VARCHAR},
      item_headline = #{itemHeadline,jdbcType=VARCHAR},
      item_sub_headline = #{itemSubHeadline,jdbcType=VARCHAR},
      item_description = #{itemDescription,jdbcType=VARCHAR},
      item_address = #{itemAddress,jdbcType=VARCHAR},
      price = #{price,jdbcType=DECIMAL},
      image_url = #{imageUrl,jdbcType=VARCHAR},
      item_category = #{itemCategory,jdbcType=INTEGER},
      sale_price = #{salePrice,jdbcType=DECIMAL},
      remarketing_url = #{remarketingUrl,jdbcType=VARCHAR},
      destination_url = #{destinationUrl,jdbcType=VARCHAR},
      final_url = #{finalUrl,jdbcType=VARCHAR},
      create_time_utc = #{createTimeUtc,jdbcType=INTEGER},
      create_user_id = #{createUserId,jdbcType=INTEGER},
      update_time_utc = #{updateTimeUtc,jdbcType=INTEGER},
      update_user_id = #{updateUserId,jdbcType=INTEGER},
      item_keywords = #{itemKeywords,jdbcType=LONGVARCHAR}
    where id = #{id,jdbcType=INTEGER}
  </update>
  <update id="updateByPrimaryKey" parameterType="com.lt.dao.model.AdAdvertiseFeed" >
    <!--
      WARNING - @mbggenerated
      This element is automatically generated by MyBatis Generator, do not modify.
      This element was generated on Mon May 04 11:11:12 CST 2015.
    -->
    update lt_ad_advertise_feed
    set ad_advertise_id = #{adAdvertiseId,jdbcType=INTEGER},
      ad_group_id = #{adGroupId,jdbcType=INTEGER},
      ad_campaign_id = #{adCampaignId,jdbcType=INTEGER},
      company_id = #{companyId,jdbcType=INTEGER},
      item_id = #{itemId,jdbcType=VARCHAR},
      item_type = #{itemType,jdbcType=VARCHAR},
      item_headline = #{itemHeadline,jdbcType=VARCHAR},
      item_sub_headline = #{itemSubHeadline,jdbcType=VARCHAR},
      item_description = #{itemDescription,jdbcType=VARCHAR},
      item_address = #{itemAddress,jdbcType=VARCHAR},
      price = #{price,jdbcType=DECIMAL},
      image_url = #{imageUrl,jdbcType=VARCHAR},
      item_category = #{itemCategory,jdbcType=INTEGER},
      sale_price = #{salePrice,jdbcType=DECIMAL},
      remarketing_url = #{remarketingUrl,jdbcType=VARCHAR},
      destination_url = #{destinationUrl,jdbcType=VARCHAR},
      final_url = #{finalUrl,jdbcType=VARCHAR},
      create_time_utc = #{createTimeUtc,jdbcType=INTEGER},
      create_user_id = #{createUserId,jdbcType=INTEGER},
      update_time_utc = #{updateTimeUtc,jdbcType=INTEGER},
      update_user_id = #{updateUserId,jdbcType=INTEGER}
    where id = #{id,jdbcType=INTEGER}
  </update>
  
  <!-- 自定义 -->
  <resultMap id="ExetendMap" type="com.lt.dao.po.AdAdvertiseFeedPO" extends="ResultMapWithBLOBs" >
    <result column="company_name" property="companyName" jdbcType="VARCHAR" />
    <result column="campaign_name" property="campaignName" jdbcType="VARCHAR" />
    <result column="group_name" property="groupName" jdbcType="VARCHAR" />
    <result column="ad_name" property="adName" jdbcType="VARCHAR" />
  </resultMap>
  
  <select id="getAdFeedList" resultMap="ExetendMap" parameterType="com.lt.dao.po.AdAdvertiseFeedPO" >
    select 
        c.`name` company_name,ac.`name` campaign_name,ag.`name` group_name, aa.name ad_name, aaf.*
    from 
        lt_ad_advertise aa
        left join lt_ad_advertise_feed aaf on aa.id=aaf.ad_advertise_id 
        left join lt_company c on aaf.company_id=c.id
        left join lt_ad_campaign ac on aaf.ad_campaign_id=ac.id
        left join lt_ad_group ag on aaf.ad_group_id=ag.id
    <where>
      <if test="id != null" >
        aaf.id = #{id,jdbcType=INTEGER}
      </if>
      <if test="adGroupId != null" >
        and aaf.ad_group_id = #{adGroupId,jdbcType=INTEGER}
      </if>
      <if test="adCampaignId != null" >
        and aaf.ad_campaign_id = #{adCampaignId,jdbcType=INTEGER}
      </if>
      <if test="companyId != null" >
        and aaf.company_id = #{companyId,jdbcType=INTEGER}
      </if>
    </where>
  </select>
</mapper>