<?xml version="1.0" encoding="UTF-8" ?>
<!DOCTYPE mapper PUBLIC "-//mybatis.org//DTD Mapper 3.0//EN" "http://mybatis.org/dtd/mybatis-3-mapper.dtd" >
<mapper namespace="com.lt.dao.mapper.AppLogMapper" >
  <resultMap id="BaseResultMap" type="com.lt.dao.model.AppLog" >
    <!--
      WARNING - @mbggenerated
      This element is automatically generated by MyBatis Generator, do not modify.
      This element was generated on Tue Mar 17 14:35:43 GMT+08:00 2015.
    -->
    <id column="id" property="id" jdbcType="INTEGER" />
    <result column="level" property="level" jdbcType="VARCHAR" />
    <result column="category" property="category" jdbcType="VARCHAR" />
    <result column="logtime" property="logtime" jdbcType="INTEGER" />
  </resultMap>
  <resultMap id="ResultMapWithBLOBs" type="com.lt.dao.model.AppLog" extends="BaseResultMap" >
    <!--
      WARNING - @mbggenerated
      This element is automatically generated by MyBatis Generator, do not modify.
      This element was generated on Tue Mar 17 14:35:43 GMT+08:00 2015.
    -->
    <result column="message" property="message" jdbcType="LONGVARCHAR" />
  </resultMap>
  <sql id="Base_Column_List" >
    <!--
      WARNING - @mbggenerated
      This element is automatically generated by MyBatis Generator, do not modify.
      This element was generated on Tue Mar 17 14:35:43 GMT+08:00 2015.
    -->
    id, level, category, logtime
  </sql>
  <sql id="Blob_Column_List" >
    <!--
      WARNING - @mbggenerated
      This element is automatically generated by MyBatis Generator, do not modify.
      This element was generated on Tue Mar 17 14:35:43 GMT+08:00 2015.
    -->
    message
  </sql>
  <select id="selectByPrimaryKey" resultMap="ResultMapWithBLOBs" parameterType="java.lang.Integer" >
    <!--
      WARNING - @mbggenerated
      This element is automatically generated by MyBatis Generator, do not modify.
      This element was generated on Tue Mar 17 14:35:43 GMT+08:00 2015.
    -->
    select 
    <include refid="Base_Column_List" />
    ,
    <include refid="Blob_Column_List" />
    from lt_applog
    where id = #{id,jdbcType=INTEGER}
  </select>
  <delete id="deleteByPrimaryKey" parameterType="java.lang.Integer" >
    <!--
      WARNING - @mbggenerated
      This element is automatically generated by MyBatis Generator, do not modify.
      This element was generated on Tue Mar 17 14:35:43 GMT+08:00 2015.
    -->
    delete from lt_applog
    where id = #{id,jdbcType=INTEGER}
  </delete>
  <insert id="insert" parameterType="com.lt.dao.model.AppLog" >
    <!--
      WARNING - @mbggenerated
      This element is automatically generated by MyBatis Generator, do not modify.
      This element was generated on Tue Mar 17 14:35:43 GMT+08:00 2015.
    -->
    insert into lt_applog (id, level, category, 
      logtime, message)
    values (#{id,jdbcType=INTEGER}, #{level,jdbcType=VARCHAR}, #{category,jdbcType=VARCHAR}, 
      #{logtime,jdbcType=INTEGER}, #{message,jdbcType=LONGVARCHAR})
  </insert>
  <insert id="insertSelective" parameterType="com.lt.dao.model.AppLog" >
    <!--
      WARNING - @mbggenerated
      This element is automatically generated by MyBatis Generator, do not modify.
      This element was generated on Tue Mar 17 14:35:43 GMT+08:00 2015.
    -->
    insert into lt_applog
    <trim prefix="(" suffix=")" suffixOverrides="," >
      <if test="id != null" >
        id,
      </if>
      <if test="level != null" >
        level,
      </if>
      <if test="category != null" >
        category,
      </if>
      <if test="logtime != null" >
        logtime,
      </if>
      <if test="message != null" >
        message,
      </if>
    </trim>
    <trim prefix="values (" suffix=")" suffixOverrides="," >
      <if test="id != null" >
        #{id,jdbcType=INTEGER},
      </if>
      <if test="level != null" >
        #{level,jdbcType=VARCHAR},
      </if>
      <if test="category != null" >
        #{category,jdbcType=VARCHAR},
      </if>
      <if test="logtime != null" >
        #{logtime,jdbcType=INTEGER},
      </if>
      <if test="message != null" >
        #{message,jdbcType=LONGVARCHAR},
      </if>
    </trim>
  </insert>
  <update id="updateByPrimaryKeySelective" parameterType="com.lt.dao.model.AppLog" >
    <!--
      WARNING - @mbggenerated
      This element is automatically generated by MyBatis Generator, do not modify.
      This element was generated on Tue Mar 17 14:35:43 GMT+08:00 2015.
    -->
    update lt_applog
    <set >
      <if test="level != null" >
        level = #{level,jdbcType=VARCHAR},
      </if>
      <if test="category != null" >
        category = #{category,jdbcType=VARCHAR},
      </if>
      <if test="logtime != null" >
        logtime = #{logtime,jdbcType=INTEGER},
      </if>
      <if test="message != null" >
        message = #{message,jdbcType=LONGVARCHAR},
      </if>
    </set>
    where id = #{id,jdbcType=INTEGER}
  </update>
  <update id="updateByPrimaryKeyWithBLOBs" parameterType="com.lt.dao.model.AppLog" >
    <!--
      WARNING - @mbggenerated
      This element is automatically generated by MyBatis Generator, do not modify.
      This element was generated on Tue Mar 17 14:35:43 GMT+08:00 2015.
    -->
    update lt_applog
    set level = #{level,jdbcType=VARCHAR},
      category = #{category,jdbcType=VARCHAR},
      logtime = #{logtime,jdbcType=INTEGER},
      message = #{message,jdbcType=LONGVARCHAR}
    where id = #{id,jdbcType=INTEGER}
  </update>
  <update id="updateByPrimaryKey" parameterType="com.lt.dao.model.AppLog" >
    <!--
      WARNING - @mbggenerated
      This element is automatically generated by MyBatis Generator, do not modify.
      This element was generated on Tue Mar 17 14:35:43 GMT+08:00 2015.
    -->
    update lt_applog
    set level = #{level,jdbcType=VARCHAR},
      category = #{category,jdbcType=VARCHAR},
      logtime = #{logtime,jdbcType=INTEGER}
    where id = #{id,jdbcType=INTEGER}
  </update>
</mapper>